create_rag_app/__init__.py
create_rag_app/cli.py
create_rag_app/components/__init__.py
create_rag_app/components/base.py
create_rag_app/components/chunking/__init__.py
create_rag_app/components/chunking/fixed_size.py
create_rag_app/components/chunking/semantic.py
create_rag_app/components/embedding/__init__.py
create_rag_app/components/embedding/all_minilm.py
create_rag_app/components/embedding/jina.py
create_rag_app/components/llm/__init__.py
create_rag_app/components/llm/hf.py
create_rag_app/components/llm/local.py
create_rag_app/components/llm/openai.py
create_rag_app/components/retriever/__init__.py
create_rag_app/components/retriever/dense.py
create_rag_app/components/retriever/hybrid.py
create_rag_app/components/retriever/sparse.py
create_rag_app/components/vectorstore/qdrant.py
create_rag_app/main.py
create_rag_app/templates/Dockerfile.backend.j2
create_rag_app/templates/Dockerfile.frontend.j2
create_rag_app/templates/app.py.j2
create_rag_app/templates/config.py.j2
create_rag_app/templates/docker-compose.yml.j2
create_rag_app/templates/env.j2
create_rag_app/templates/frontend.py.j2
create_rag_app/templates/requirements.txt.j2
create_rag_app/templates/src/generator.py.j2
create_rag_app/templates/src/rag_pipeline.py.j2
create_rag_app/templates/src/utils/embedder.py.j2
create_rag_app/templates/src/utils/loader.py.j2
create_rag_app/templates/src/vectorstore.py.j2
create_rag_app-0.1.2.dist-info/METADATA
create_rag_app-0.1.2.dist-info/WHEEL
create_rag_app-0.1.2.dist-info/entry_points.txt
create_rag_app-0.1.2.dist-info/RECORD
