Metadata-Version: 2.3
Name: create-rag-app
Version: 0.1.2
Summary: A command-line tool to generate modern RAG applications with various components.
Author: Syed-MuhammadTaha
Author-email: simam.bscs22seecs@seecs.edu.pk
Requires-Python: >=3.12
Classifier: Programming Language :: Python :: 3
Classifier: Programming Language :: Python :: 3.12
Classifier: Programming Language :: Python :: 3.13
Requires-Dist: jinja2 (>=3.1.6,<4.0.0)
Requires-Dist: questionary (>=2.1.0,<3.0.0)
Requires-Dist: typer (>=0.16.0,<0.17.0)
Project-URL: Homepage, https://github.com/Syed-MuhammadTaha/create-rag-app
Project-URL: Repository, https://github.com/Syed-MuhammadTaha/create-rag-app
